[{"version":"3.0.1","hash":"92a5b089020b9803f30fab1a733c3251","ngwHash":"cfcd208495d565ef66e7dff9f98764da","cachedDate":1517197554874,"gaData":[{"updated":"Mon Jan 29 2018 11:44:31 GMT+0800 (中国标准时间)","title":"markdown图片批量下载小工具","path":"other/markdown_img_download/","eyeCatchImage":null,"excerpt":"<hr>\n<p>前言：针对markdown文件的批量上传及批量迁移，对应已经有很好的图形化工具<a href=\"https://www.toolinbox.net/iPic/\" target=\"_blank\" rel=\"noopener\">ipic</a>及ipic mover，但是没有将图片批量下载备份到本地的小工具，于是自己动手写了一个。</p>\n<p><img src=\"https://image-1251774567.cosgz.myqcloud.com/201801211403_697.png\" alt=\"\"></p>","date":"2017-11-06T16:00:00.000Z","pv":0,"totalPV":0,"categories":"other","tags":["markdown","image"],"internalLinks":[],"keywords":[],"keywordsLength":0},{"updated":"Mon Jan 29 2018 11:34:03 GMT+0800 (中国标准时间)","title":"","path":"uncategorized/undefined/","eyeCatchImage":null,"excerpt":null,"date":"2018-01-29T03:34:03.419Z","pv":0,"totalPV":0,"categories":"","tags":[],"internalLinks":[],"keywords":[],"keywordsLength":0},{"updated":"Tue Jan 23 2018 16:49:29 GMT+0800 (中国标准时间)","title":"Hexo的源码保存过程小记","path":"other/hexo_source2github/","eyeCatchImage":null,"excerpt":"<hr>\n<p>前言：由于差一点把调整过的hexo源码搞不见了，便想着将hexo的源码保存在云上，主要是利用github的分支，将hexo的源码和hexo的发布文件保存到同一个<code>respository</code>,从而进行不同电脑平台上的同步。</p>\n<p><img src=\"https://image-1251774567.cosgz.myqcloud.com/201801211346_58.jpg\" alt=\"\" style=\"width:100%\"></p>","date":"2017-11-02T16:00:00.000Z","pv":0,"totalPV":0,"categories":"other","tags":["hexo","github"],"internalLinks":[],"keywords":[],"keywordsLength":0},{"updated":"Wed Jan 24 2018 20:09:45 GMT+0800 (中国标准时间)","title":"计算机编码学习小记-字符编码、MIME编码","path":"tech/computer_character_encoding/","eyeCatchImage":null,"excerpt":"<hr>\n<p>前言：写这一篇文章的动机主要是在前面做<a href=\"https://kbrx93.com/other/markdown_img_download/\" target=\"_blank\" rel=\"noopener\">markdown图片批量下载小工具</a>时遇到过编码问题，发现自己对于计算机内部的编码了解甚少，于是想较为系统地学习一下。这篇笔记记录的主要是计算机内部的编码，至于在网络传输过程中编码的过程和问题以及在各种编程语言中的编码问题不在讨论范围之中，如果以后有时间或者有需要再写吧。不对或不妥之处，请批评指正。</p>\n<p><img src=\"https://image-1251774567.cosgz.myqcloud.com/201801211407_325.png\" alt=\"\"></p>","date":"2017-11-08T16:00:00.000Z","pv":0,"totalPV":0,"categories":"tech","tags":["encoding"],"internalLinks":[],"keywords":[],"keywordsLength":0},{"updated":"Tue Jan 23 2018 16:55:55 GMT+0800 (中国标准时间)","title":"计算机编码的一些后续补充","path":"tech/computer_character_encoding2/","eyeCatchImage":null,"excerpt":"<hr>\n<p>前言：写这篇笔记的目的，主要是为了补充一下前面<code>计算机编码</code>那篇笔记没有提到的在计算机内部文件存储及内存中的编码问题，以及编码转化的一些简单介绍。日后如果发现还有一些关于编码的问题需要记录也一并写在这里，就不写在之前的笔记里了。</p>","date":"2017-11-16T15:42:29.000Z","pv":0,"totalPV":0,"categories":"tech","tags":["encoding"],"internalLinks":[],"keywords":[],"keywordsLength":0},{"updated":"Sun Jan 28 2018 09:55:01 GMT+0800 (中国标准时间)","title":"关于2018的个人打算","path":"think/plan_in_2018/","eyeCatchImage":null,"excerpt":"<blockquote class=\"blockquote-center\"><p>宏愿纵未了，</p>\n<p>奋斗总不太晚。</p>\n</blockquote>\n<p><img src=\"https://image-1251774567.cosgz.myqcloud.com/2018-01-19-Article-Fubiz-Tv-45.jpg\" alt=\"\"></p>","date":"2018-01-17T16:00:00.000Z","pv":0,"totalPV":0,"categories":"think","tags":["2018","plan"],"internalLinks":[],"keywords":[],"keywordsLength":0},{"updated":"Sun Jan 28 2018 09:55:11 GMT+0800 (中国标准时间)","title":"归家","path":"think/record_back_home/","eyeCatchImage":null,"excerpt":"<blockquote class=\"blockquote-center\"><p>要是 彼此都有些 既定路程，</p>\n<p>学会洒脱，好吗</p>\n</blockquote>\n<p><img src=\"https://image-1251774567.cosgz.myqcloud.com/201801220844_179.jpg\" alt=\"\"></p>","date":"2018-01-19T16:00:00.000Z","pv":0,"totalPV":0,"categories":"think","tags":["回家","随笔"],"internalLinks":[],"keywords":[],"keywordsLength":0},{"updated":"Tue Jan 23 2018 16:55:21 GMT+0800 (中国标准时间)","title":"Java中文件读取路径学习记录","path":"tech/Java_File_Path/","eyeCatchImage":null,"excerpt":"<hr>\n<p>前言：最近在写算法题时用到从文件中读取相关记录，发现对Java读取文件时的路径不是很清楚，网上相关文章很多，在此仅作记录与自我复习使用。如有不对之处，请批评指正。</p>\n<p><img src=\"https://image-1251774567.cosgz.myqcloud.com/201801211411_886.svg\" alt=\"\"></p>","date":"2017-11-14T16:00:00.000Z","pv":0,"totalPV":0,"categories":"tech","tags":["Java","path"],"internalLinks":[],"keywords":[],"keywordsLength":0},{"updated":"Tue Jan 23 2018 16:56:14 GMT+0800 (中国标准时间)","title":"关于Mac上自动切换输入法的记录","path":"other/change_input_method/","eyeCatchImage":null,"excerpt":"<hr>\n<p>前言：首先，对于Mac上在不同应用上的输入法混乱问题我感到非常不适应，于是想搞一套可以根据应用自动切换对应输入法的工作流程（类似于百度及搜狗输入法的安静模式，但我所使用的清歌输入法却没有，加之前面两者的字排序我十分不满意，还不能手动调频，所以才想自己搞一下）。以下是过程相关记录（写得比较粗糙。。）</p>","date":"2017-12-03T14:45:54.000Z","pv":0,"totalPV":0,"categories":"other","tags":["input_method","mac"],"internalLinks":[],"keywords":[],"keywordsLength":0},{"updated":"Mon Jan 29 2018 11:27:46 GMT+0800 (中国标准时间)","title":"杂记","path":"think/random_record/","eyeCatchImage":null,"excerpt":"<blockquote class=\"blockquote-center\"><p>23,一个半醉不醒的年纪 </p>\n</blockquote>\n<p><img src=\"https://image-1251774567.cosgz.myqcloud.com/2018-01-27-124965.jpg\" alt=\"\"></p>","date":"2018-01-26T16:00:00.000Z","pv":0,"totalPV":0,"categories":"think","tags":["随便说点什么","胡说"],"internalLinks":[],"keywords":[],"keywordsLength":0}]}]